aws_mfa_helper_cli/__init__.py
aws_mfa_helper_cli/cli.py
aws_mfa_helper_cli/config.py
aws_mfa_helper_cli/utils.py
aws_mfa_helper_cli-0.1.0.dist-info/LICENSE
aws_mfa_helper_cli-0.1.0.dist-info/METADATA
aws_mfa_helper_cli-0.1.0.dist-info/WHEEL
aws_mfa_helper_cli-0.1.0.dist-info/entry_points.txt
aws_mfa_helper_cli-0.1.0.dist-info/top_level.txt
aws_mfa_helper_cli-0.1.0.dist-info/RECORD
