Metadata-Version: 2.1
Name: aws-mfa-helper-cli
Version: 0.1.0
Summary: A CLI tool to manage AWS MFA session tokens easily.
Home-page: https://github.com/amy83762100/aws-mfa-helper-cli
Author: Pei-Yi Lin
Classifier: Programming Language :: Python :: 3
Classifier: License :: OSI Approved :: MIT License
Classifier: Operating System :: OS Independent
Requires-Python: >=3.6
License-File: LICENSE
Requires-Dist: boto3
Requires-Dist: click
